[{"model": "api.article", "pk": 1, "fields": {"title": "\u30bf\u30b0\u306a\u3057", "body": "\u30bf\u30b0\u306a\u3057\u3060", "slug": "without-tag", "published": true, "created_at": "2017-04-09 12:30:00", "updated_at": "2017-04-09 12:30:00", "tags": []}}, {"model": "api.article", "pk": 2, "fields": {"title": "\u30bf\u30b0\u3042\u308a", "body": "\u30bf\u30b0\u3042\u308a\u3060", "slug": "with-tag", "published": true, "created_at": "2017-04-10 12:30:00", "updated_at": "2017-04-10 12:30:00", "tags": [1, 2]}}, {"model": "api.article", "pk": 3, "fields": {"title": "\u672a\u516c\u958b", "body": "\u672a\u516c\u958b\u3060\u3088", "slug": "not-published", "published": false, "created_at": "2017-04-11 12:30:00", "updated_at": "2017-04-11 12:30:00", "tags": []}}]